<?xml version="1.0" encoding="UTF-8"?>
<krpano>

<!-- ************************ -->
<!--         Messages         -->
<!-- ************************ -->

  <data name="en_project_title"><![CDATA[ЭЛЕКТРОМОБИЛЬ VOLKSWAGEN W487]]></data>
  <data name="en_project_author_name"><![CDATA[lenskii.ru]]></data>
  <data name="en_project_author_url"><![CDATA[http://lenskii.ru]]></data>


  <data name="en_panogroup28_title"><![CDATA[Вид спереди]]></data>

  <data name="en_pano23_title"><![CDATA[Вид спереди]]></data>
  <data name="en_spotpoint32_tooltip"><![CDATA[Вид справа]]></data>
  <data name="en_spotpoint34_tooltip"><![CDATA[Вид изнутри]]></data>
  <data name="en_spotpoint47_tooltip"><![CDATA[Вид слева]]></data>

  <data name="en_panogroup31_title"><![CDATA[Вид справа]]></data>

  <data name="en_pano26_title"><![CDATA[Вид справа]]></data>
  <data name="en_spotpoint33_tooltip"><![CDATA[Вид спереди]]></data>
  <data name="en_spotpoint42_tooltip"><![CDATA[Вид сзади]]></data>
  <data name="en_spotpoint43_tooltip"><![CDATA[Вид изнутри]]></data>

  <data name="en_panogroup29_title"><![CDATA[Вид сзади]]></data>

  <data name="en_pano24_title"><![CDATA[Вид сзади]]></data>
  <data name="en_spotpoint39_tooltip"><![CDATA[Вид изнутри]]></data>
  <data name="en_spotpoint40_tooltip"><![CDATA[Вид слева]]></data>
  <data name="en_spotpoint41_tooltip"><![CDATA[Вид справа]]></data>

  <data name="en_panogroup30_title"><![CDATA[Вид слева]]></data>

  <data name="en_pano25_title"><![CDATA[Вид слева]]></data>
  <data name="en_spotpoint44_tooltip"><![CDATA[Вид спереди]]></data>
  <data name="en_spotpoint45_tooltip"><![CDATA[Вид изнутри]]></data>
  <data name="en_spotpoint46_tooltip"><![CDATA[Вид сзади]]></data>

  <data name="en_panogroup27_title"><![CDATA[Вид изнутри]]></data>

  <data name="en_pano22_title"><![CDATA[Вид изнутри]]></data>
  <data name="en_spotpoint35_tooltip"><![CDATA[Вид спереди]]></data>
  <data name="en_spotpoint36_tooltip"><![CDATA[Вид слева]]></data>
  <data name="en_spotpoint37_tooltip"><![CDATA[Вид справа]]></data>
  <data name="en_spotpoint38_tooltip"><![CDATA[Вид сзади]]></data>






  <data name="en_contextmenuopenFsLabel"><![CDATA[Enter Fullscreen]]></data>
  <data name="en_contextmenucloseFsLabel"><![CDATA[Exit Fullscreen]]></data>
  <data name="en_contextmenunormallabel"><![CDATA[Normal View]]></data>
  <data name="en_contextmenuarchitecturallabel"><![CDATA[Architectural View]]></data>
  <data name="en_contextmenulittleplanetlabel"><![CDATA[Little Planet View]]></data>
  <data name="en_buttontooltip"><![CDATA[Официальный сайт производителя]]></data>
  <data name="en_buttononclick10212openurlwebsiteurl"><![CDATA[https://viptoys.ru.com/]]></data>


  <data name="en_vr_setup_hmd0"><![CDATA[SELECT YOUR HMD]]></data>
  <data name="en_vr_setup_advanced"><![CDATA[ADVANCED SETTINGS]]></data>
  <data name="en_vr_setup_title"><![CDATA[WEB VR SETTINGS]]></data>
  <data name="en_vr_setup_dvn1"><![CDATA[Device:]]></data>
  <data name="en_vr_setup_siz1"><![CDATA[Screen size:]]></data>
  <data name="en_vr_setup_ipd1"><![CDATA[IPD:]]></data>
  <data name="en_vr_setup_hmd1"><![CDATA[HMD:]]></data>
  <data name="en_vr_setup_hmd3"><![CDATA[Customize]]></data>
  <data name="en_vr_setup_cal"><![CDATA[Calibrate gyroscope]]></data>
  <data name="en_vr_setup_sav"><![CDATA[SAVE]]></data>
  <data name="en_vr_setup_rst"><![CDATA[RESET]]></data>
  <data name="en_vr_setup_simple"><![CDATA[SIMPLE]]></data>
  <data name="en_vr_setup_cls"><![CDATA[CLOSE]]></data>
  <data name="en_vr_setup_m31"><![CDATA[HMD SETTINGS]]></data>
  <data name="en_vr_setup_fov1"><![CDATA[FOV:]]></data>
  <data name="en_vr_setup_dst1"><![CDATA[Distortion:]]></data>
  <data name="en_vr_setup_d2tx"><![CDATA[Distortion 2:]]></data>
  <data name="en_vr_setup_vig1"><![CDATA[Vignette:]]></data>
  <data name="en_vr_setup_cac1"><![CDATA[Chromatic aberration:]]></data>
  <data name="en_vr_setup_olp1"><![CDATA[Overlap:]]></data>
  <data name="en_vr_setup_m35"><![CDATA[RETURN]]></data>
  <data name="en_vr_setup_cb1"><![CDATA[GYROSCOPE]]></data>
  <data name="en_vr_setup_cb2"><![CDATA[Place the device on a flat and[br]stable surface and tab CALIBRATE[br]to correct a gyroscope drifting.]]></data>
  <data name="en_vr_setup_cb3"><![CDATA[CALIBRATE]]></data>
  <data name="en_vr_setup_cb4"><![CDATA[RESET]]></data>
  <data name="en_vr_setup_cb5"><![CDATA[RETURN]]></data>
  <data name="en_vr_setup_cb6"><![CDATA[Calibrating...]]></data>
  <data name="en_vr_setup_cb7"><![CDATA[Successful calibration]]></data>
  <data name="en_vr_setup_cb8"><![CDATA[Calibration failed]]></data>
  <data name="en_vr_setup_unavailable"><![CDATA[VR mode[br]is unavailable on your device]]></data>


  <data name="en_project_description"><![CDATA[<font size="4" face="verdana, sans-serif"><b>Электромобиль Vip Toys Volkswagen W487</b> — такой красивый и красочный подарок принесет вашему малышу множество положительных эмоций и радости. Ведь теперь он сможет почувствовать себя настоящим водителем автобуса, спешащим за пассажирами. Реалистичная модель со звуковыми и световыми эффектами. Прочная и надежная конструкция из усиленного и противоударного полипропилена, экологически чистая и безопасная краска. Электромобиль поможет вашему малышу развить чувство ответственности, внимания и познать правила дорожного движения.</font>]]></data>



  <data name="en_spotpoint32_description"><![CDATA[Это вид справа 111111]]></data>
  <data name="en_spotpoint47_description"><![CDATA[Это вид слева]]></data>













</krpano>